<?xml version="1.0" encoding="UTF-8"?>

<ApolloNavigations xmlns:xsi="http://www.w3.org/2001/XMLSchema-instance" xsi:noNamespaceSchemaLocation="opencms://system/modules/org.opencms.apollo.template.schemas/schemas/navigation.xsd">
  <ApolloNavigation language="en">
    <Title><![CDATA[Second Level navigation]]></Title>
    <NavStartLevel><![CDATA[2]]></NavStartLevel>
    <LogoImage/>
    <LogoLink>
      <link internal="true" type="WEAK">
        <target><![CDATA[/sites/default/]]></target>
        <uuid>49695aa2-f002-11e5-a794-0242ac11002b</uuid>
      </link>
    </LogoLink>
    <Header name="Header0">
      <links/>
      <content/>
    </Header>
  </ApolloNavigation>
</ApolloNavigations>
